fastbuild/__init__.py
fastbuild/cli.py
fastbuild/commands.py
fastbuild/exceptions.py
fastbuild/version.py
fastbuild/enum/package.py
fastbuild/snippets/__init__.py
fastbuild/snippets/init_import_snippet.py
fastbuild/snippets/settings_db_methods.py
fastbuild/snippets/settings_db_vars.py
fastbuild/template/database/__init__.py
fastbuild/template/database/connection.py
fastbuild/template/database/populate.py
fastbuild/template/default/main.py
fastbuild/template/default/src/__init__.py
fastbuild/template/default/src/configuration/__init__.py
fastbuild/template/default/src/configuration/settings.py
fastbuild/template/default/src/routes/__init__.py
fastbuild/template/default/src/routes/home.py
fastbuild/template/default/src/utils/__init__.py
fastbuild/template/default/tests/__init__.py
fastbuild/tests/__init__.py
fastbuild/utils/__init__.py
fastbuild-0.1.1.dist-info/licenses/LICENSE
fastbuild-0.1.1.dist-info/METADATA
fastbuild-0.1.1.dist-info/WHEEL
fastbuild-0.1.1.dist-info/entry_points.txt
fastbuild-0.1.1.dist-info/top_level.txt
fastbuild-0.1.1.dist-info/RECORD
