Metadata-Version: 2.4
Name: fastbuild
Version: 0.1.1
Summary: CLI tool to bootstrap FastAPI projects
Author-email: Leonan <leonan.thomaz@gmail.com>
License-Expression: MIT
Requires-Python: >=3.8
License-File: LICENSE
Requires-Dist: fastapi
Requires-Dist: uvicorn
Requires-Dist: click
Requires-Dist: python-dotenv
Dynamic: license-file
